athenah_ai/agent/__init__.py
athenah_ai/agent/models.py
athenah_ai/agent/prompts.py
athenah_ai/agent/tools/fs/shell.py
athenah_ai/agent/tools/fs/utils.py
athenah_ai/agent/tools/github/diff_tools.py
athenah_ai/basedir.py
athenah_ai/client/__init__.py
athenah_ai/client/file_handler.py
athenah_ai/client/llm_adapters.py
athenah_ai/client/tools.py
athenah_ai/client/vector_store.py
athenah_ai/config.py
athenah_ai/dist/test_collection_stats/test_collection_stats-source/BuildInfo.cpp.txt
athenah_ai/dist/test_collection_stats-v1/1ce02783-0452-4a21-b302-b22159bc6535/data_level0.bin
athenah_ai/dist/test_collection_stats-v1/1ce02783-0452-4a21-b302-b22159bc6535/header.bin
athenah_ai/dist/test_collection_stats-v1/1ce02783-0452-4a21-b302-b22159bc6535/length.bin
athenah_ai/dist/test_collection_stats-v1/1ce02783-0452-4a21-b302-b22159bc6535/link_lists.bin
athenah_ai/dist/test_collection_stats-v1/chroma.sqlite3
athenah_ai/dist/test_collection_stats-v1/split_0.txt
athenah_ai/dist/test_index_dir/test_index_dir-source/BuildInfo.cpp.txt
athenah_ai/dist/test_index_dir/test_index_dir-source/subfixture/RCLConsensus.cpp.txt
athenah_ai/dist/test_index_dir-v1/3a1890ff-019c-4150-9b4e-d5ac24b86cb4/data_level0.bin
athenah_ai/dist/test_index_dir-v1/3a1890ff-019c-4150-9b4e-d5ac24b86cb4/header.bin
athenah_ai/dist/test_index_dir-v1/3a1890ff-019c-4150-9b4e-d5ac24b86cb4/length.bin
athenah_ai/dist/test_index_dir-v1/3a1890ff-019c-4150-9b4e-d5ac24b86cb4/link_lists.bin
athenah_ai/dist/test_index_dir-v1/chroma.sqlite3
athenah_ai/dist/test_index_dir-v1/split_0.txt
athenah_ai/dist/test_index_dir-v1/split_1.txt
athenah_ai/dist/test_index_dir-v1/split_2.txt
athenah_ai/dist/test_index_dir-v1/split_3.txt
athenah_ai/dist/test_index_dir-v1/split_4.txt
athenah_ai/dist/test_index_file/test_index_file-source/BuildInfo.cpp.txt
athenah_ai/dist/test_index_file-v1/3c40071e-46fb-4340-9917-ccbf6acf6f4f/data_level0.bin
athenah_ai/dist/test_index_file-v1/3c40071e-46fb-4340-9917-ccbf6acf6f4f/header.bin
athenah_ai-4.0.6.dist-info/METADATA
athenah_ai-4.0.6.dist-info/WHEEL
athenah_ai-4.0.6.dist-info/RECORD
