Metadata-Version: 2.3
Name: athenah-ai
Version: 4.0.6
Summary: 
Author: Denis Angell
Author-email: dangell@transia.co
Requires-Python: >=3.10.6,<4.0.0
Classifier: Programming Language :: Python :: 3
Classifier: Programming Language :: Python :: 3.11
Classifier: Programming Language :: Python :: 3.12
Classifier: Programming Language :: Python :: 3.13
Requires-Dist: anthropic (>=0.75.0,<0.76.0)
Requires-Dist: chromadb (>=1.3.7,<2.0.0)
Requires-Dist: google-cloud-storage (>=3.4.0,<4.0.0)
Requires-Dist: langchain (==1.1.0)
Requires-Dist: langchain-anthropic (==1.2.0)
Requires-Dist: langchain-community (==0.4.1)
Requires-Dist: langchain-core (==1.1.0)
Requires-Dist: langchain-openai (==1.1.0)
Requires-Dist: langchain-xai (==1.1.0)
Requires-Dist: langgraph (==1.0.4)
Requires-Dist: langgraph-prebuilt (==1.0.5)
Requires-Dist: langsmith (==0.4.38)
Requires-Dist: openai (>=2.6.1,<3.0.0)
Requires-Dist: python-dotenv (>=1.2.1,<2.0.0)
Requires-Dist: scikit-learn (>=1.6.0,<2.0.0)
Requires-Dist: tabulate (>=0.9.0,<0.10.0)
Requires-Dist: tiktoken (>=0.11.0,<0.12.0)
Requires-Dist: unstructured[local-inference] (>=0.6.2,<0.7.0)
